host_user_override/__init__.py
host_user_override/apps.py
host_user_override/conf.py
host_user_override/middleware.py
host_user_override/tests.py
host_user_override/utils.py
host_user_override/locale/ru/LC_MESSAGES/django.mo
host_user_override/locale/ru/LC_MESSAGES/django.po
host_user_override/static/host_user_override/style.css
host_user_override/templates/host_user_override/banner.html
host_user_override/templates/host_user_override/change_form.html
host_user_override/templatetags/__init__.py
host_user_override/templatetags/host_user_override.py
django_host_user_override-0.4.5.dist-info/LICENSE
django_host_user_override-0.4.5.dist-info/METADATA
django_host_user_override-0.4.5.dist-info/WHEEL
django_host_user_override-0.4.5.dist-info/top_level.txt
django_host_user_override-0.4.5.dist-info/RECORD
